{"retweet":"GirlPosts","sum_emotion":[6724,2805,15924,7470,14990],"sum_sentiment":[15045,24548,8320],"total":47913,"month":"08"}
{"retweet":"BigHitEnt","sum_emotion":[37157,1,0,0,20],"sum_sentiment":[37118,56,4],"total":37178,"month":"08"}
{"retweet":"realDonaldTrump","sum_emotion":[13962,1756,5233,818,15314],"sum_sentiment":[20640,5321,11122],"total":37083,"month":"08"}
{"retweet":"iamwilliewill","sum_emotion":[7137,1320,10561,611,11425],"sum_sentiment":[12050,13355,5649],"total":31054,"month":"08"}
{"retweet":"BarackObama","sum_emotion":[3736,3,6731,143,18366],"sum_sentiment":[5931,18528,4520],"total":28979,"month":"08"}
{"retweet":"funder","sum_emotion":[2649,1224,10355,1016,11020],"sum_sentiment":[6848,13197,6219],"total":26264,"month":"08"}
{"retweet":"FreddyAmazin","sum_emotion":[4653,1146,7695,2357,8816],"sum_sentiment":[9710,11006,3951],"total":24667,"month":"08"}
{"retweet":"BleacherReport","sum_emotion":[9562,1766,3431,1169,6688],"sum_sentiment":[5749,14018,2849],"total":22616,"month":"08"}
{"retweet":"lordflaconegro","sum_emotion":[4028,1249,9845,709,6424],"sum_sentiment":[4487,14951,2817],"total":22255,"month":"08"}
{"retweet":"Gurmeetramrahim","sum_emotion":[13665,222,2032,7,4840],"sum_sentiment":[14450,5034,1282],"total":20766,"month":"08"}
{"retweet":"FoxNews","sum_emotion":[4479,1537,4985,994,8080],"sum_sentiment":[6258,9687,4130],"total":20075,"month":"08"}
{"retweet":"RealJamesWoods","sum_emotion":[3143,1419,4801,644,9494],"sum_sentiment":[7545,7498,4458],"total":19501,"month":"08"}
{"retweet":"soompi","sum_emotion":[13371,1051,1213,626,2299],"sum_sentiment":[9777,7635,1148],"total":18560,"month":"08"}
{"retweet":"kylegriffin1","sum_emotion":[3479,1022,3650,862,9308],"sum_sentiment":[5733,9087,3501],"total":18321,"month":"08"}
{"retweet":"SoDamnTrue","sum_emotion":[3049,1069,5691,1697,5747],"sum_sentiment":[5553,8370,3330],"total":17253,"month":"08"}
{"retweet":"rapspotlights","sum_emotion":[9271,1110,1682,1220,3036],"sum_sentiment":[4963,9944,1412],"total":16319,"month":"08"}
{"retweet":"ItsFoodPorn","sum_emotion":[11769,868,975,1044,1021],"sum_sentiment":[1768,12074,1835],"total":15677,"month":"08"}
{"retweet":"ShaunKing","sum_emotion":[1144,721,5061,627,8123],"sum_sentiment":[4568,3190,7918],"total":15676,"month":"08"}
{"retweet":"thehill","sum_emotion":[2650,1439,3137,463,7826],"sum_sentiment":[3556,9357,2602],"total":15515,"month":"08"}
{"retweet":"NasMaraj","sum_emotion":[918,631,6092,440,6957],"sum_sentiment":[5214,6312,3512],"total":15038,"month":"08"}
{"retweet":"CauseWereGuys","sum_emotion":[2655,1210,5078,859,4866],"sum_sentiment":[4151,7950,2567],"total":14668,"month":"08"}
{"retweet":"LaurenJauregui","sum_emotion":[4944,1244,3782,1150,3496],"sum_sentiment":[6144,5256,3216],"total":14616,"month":"08"}
{"retweet":"broebong","sum_emotion":[2701,3052,3408,246,5088],"sum_sentiment":[1539,10822,2134],"total":14495,"month":"08"}
{"retweet":"JoyAnnReid","sum_emotion":[1954,927,3600,804,7080],"sum_sentiment":[5794,5420,3151],"total":14365,"month":"08"}
{"retweet":"OriginalFunko","sum_emotion":[13491,16,27,34,776],"sum_sentiment":[13875,332,137],"total":14344,"month":"08"}
{"retweet":"PrisonPlanet","sum_emotion":[1869,631,5377,505,5836],"sum_sentiment":[5030,4338,4850],"total":14218,"month":"08"}
{"retweet":"Harrys1DEmpire","sum_emotion":[1,0,10453,0,3288],"sum_sentiment":[39,13703,0],"total":13742,"month":"08"}
{"retweet":"Camila_Cabello","sum_emotion":[9008,593,823,111,2708],"sum_sentiment":[7479,4740,1024],"total":13243,"month":"08"}
{"retweet":"mitchellvii","sum_emotion":[1397,793,3220,294,7538],"sum_sentiment":[5023,3525,4694],"total":13242,"month":"08"}
{"retweet":"shellywelly53","sum_emotion":[3199,902,4910,43,3911],"sum_sentiment":[5986,3024,3955],"total":12965,"month":"08"}
{"retweet":"CNN","sum_emotion":[2594,794,2793,544,6154],"sum_sentiment":[3965,6131,2783],"total":12879,"month":"08"}
{"retweet":"datassque","sum_emotion":[1075,1255,5675,1242,3370],"sum_sentiment":[2509,5368,4740],"total":12617,"month":"08"}
{"retweet":"ManUtd","sum_emotion":[6371,1287,561,1184,3155],"sum_sentiment":[6173,5587,798],"total":12558,"month":"08"}
{"retweet":"Salvesayson","sum_emotion":[2718,341,3581,144,5262],"sum_sentiment":[6296,3576,2174],"total":12046,"month":"08"}
{"retweet":"chuuzus","sum_emotion":[2325,47,5600,307,3640],"sum_sentiment":[3549,4890,3480],"total":11919,"month":"08"}
{"retweet":"BIacknMild","sum_emotion":[1502,1453,5150,381,3320],"sum_sentiment":[4679,5858,1269],"total":11806,"month":"08"}
{"retweet":"JackedYoTweets","sum_emotion":[1724,1393,4131,244,4218],"sum_sentiment":[2426,6647,2637],"total":11710,"month":"08"}
{"retweet":"INDIEWASHERE","sum_emotion":[636,483,3393,186,6995],"sum_sentiment":[5774,2748,3171],"total":11693,"month":"08"}
{"retweet":"Impeach_D_Trump","sum_emotion":[1582,665,4535,273,4625],"sum_sentiment":[3679,5483,2518],"total":11680,"month":"08"}
{"retweet":"iamblackbear","sum_emotion":[1861,585,2441,160,6379],"sum_sentiment":[2175,6099,3152],"total":11426,"month":"08"}
{"retweet":"SexualGif","sum_emotion":[1918,598,4413,414,4039],"sum_sentiment":[3045,6353,1984],"total":11382,"month":"08"}
{"retweet":"SincerelyTumblr","sum_emotion":[1870,785,3684,913,4118],"sum_sentiment":[4615,4504,2251],"total":11370,"month":"08"}
{"retweet":"GraysonDolan","sum_emotion":[4518,771,2481,194,3240],"sum_sentiment":[4547,4659,1998],"total":11204,"month":"08"}
{"retweet":"Dory","sum_emotion":[1709,724,3766,989,3925],"sum_sentiment":[3595,5357,2161],"total":11113,"month":"08"}
{"retweet":"BTS_twt","sum_emotion":[7256,257,32,2991,515],"sum_sentiment":[4691,6340,20],"total":11051,"month":"08"}
{"retweet":"jinjjarevil","sum_emotion":[4321,836,2199,924,2675],"sum_sentiment":[4546,5528,881],"total":10955,"month":"08"}
{"retweet":"Tyonna_Moss","sum_emotion":[1690,880,4323,257,3569],"sum_sentiment":[2565,5039,3115],"total":10719,"month":"08"}
{"retweet":"Louis_Tomlinson","sum_emotion":[5751,916,1271,253,2488],"sum_sentiment":[5420,3291,1968],"total":10679,"month":"08"}
{"retweet":"NiallOfficial","sum_emotion":[4096,1774,1025,1024,2384],"sum_sentiment":[6377,3045,881],"total":10303,"month":"08"}
{"retweet":"DineshDSouza","sum_emotion":[678,351,2667,268,6303],"sum_sentiment":[3646,3758,2863],"total":10267,"month":"08"}
